product_marketing_agency/__init__.py
product_marketing_agency/main.py
product_marketing_agency-1.0.1.dist-info/LICENSE
product_marketing_agency-1.0.1.dist-info/METADATA
product_marketing_agency-1.0.1.dist-info/WHEEL
product_marketing_agency-1.0.1.dist-info/RECORD
