Metadata-Version: 2.3
Name: product-marketing-agency
Version: 1.0.1
Summary: A comprehensive multi-agent marketing system for generating various types of product marketing images and content using the swarms framework
License: MIT
Keywords: marketing,product photography,ai agents,swarms,image generation,marketing automation,multi-agent systems,content creation,e-commerce
Author: The Swarm Corporation
Author-email: kye@swarms.world
Requires-Python: >=3.10,<4.0
Classifier: Development Status :: 4 - Beta
Classifier: Intended Audience :: Developers
Classifier: Intended Audience :: End Users/Desktop
Classifier: License :: OSI Approved :: MIT License
Classifier: Programming Language :: Python :: 3
Classifier: Programming Language :: Python :: 3.10
Classifier: Programming Language :: Python :: 3.11
Classifier: Programming Language :: Python :: 3.12
Classifier: Programming Language :: Python :: 3.13
Classifier: Topic :: Multimedia :: Graphics
Classifier: Topic :: Office/Business
Classifier: Topic :: Scientific/Engineering :: Artificial Intelligence
Requires-Dist: loguru
Requires-Dist: python-dotenv
Requires-Dist: rich
Requires-Dist: swarms
Project-URL: Documentation, https://github.com/The-Swarm-Corporation/Product-Marketing-Agency/blob/main/docs/README.md
Project-URL: Homepage, https://github.com/The-Swarm-Corporation/Product-Marketing-Agency
Project-URL: Repository, https://github.com/The-Swarm-Corporation/Product-Marketing-Agency
